aozorabunko_extractor/__init__.py
aozorabunko_extractor/cli.py
aozorabunko_extractor-0.1.0.dist-info/entry_points.txt
aozorabunko_extractor-0.1.0.dist-info/WHEEL
aozorabunko_extractor-0.1.0.dist-info/METADATA
aozorabunko_extractor-0.1.0.dist-info/RECORD
