Metadata-Version: 2.1
Name: aozorabunko-extractor
Version: 0.1.0
Summary: 
Home-page: https://github.com/hpprc/aozorabunko-extractor
Author: hppRC
Author-email: hpp.ricecake@gmail.com
Requires-Python: >=3.8,<4.0
Classifier: Programming Language :: Python :: 3
Classifier: Programming Language :: Python :: 3.8
Requires-Dist: konoha (>=4.6.2,<5.0.0)
Project-URL: Repository, https://github.com/hpprc/aozorabunko-extractor
